Workbook

Sheet Summary
B2: Atliq Sales and CRM Assistant — Cost Estimation Summary
B3: AtliQ Sales & CRM Assistant · all figures recalculate from the Inference, Backfill & Evals and Cost Savings sheets
B5: Running cost | E5: Model choice (monthly, same volume)
B6: Metric | C6: Value | E6: Model | F6: Cost per source ($) | G6: Cost per month ($)
B7: Emails / notes processed per month | C7: =Inference!C16 -> 704 | E7: =Inference!F6 -> gpt-6-astra | F7: =Inference!K6 -> 0.10328 | G7: =Inference!L6 -> 72.70912
B8: Cost per source (gpt-6-luna, incl. buffer) | C8: =Inference!G16 -> 0.00123936 | E8: =Inference!F7 -> gpt-6.1-sol | F8: =Inference!K7 -> 0.020656 | G8: =Inference!L7 -> 14.541824
B9: AI inference per month | C9: =Inference!G15 -> 0.87250944 | E9: =Inference!F8 -> gpt-6-luna (selected) | F9: =Inference!K8 -> 0.0010328 | G9: =Inference!L8 -> 0.7270912
B10: One-time backfill + first-year evals | C10: ='Backfill & Evals'!D32 -> 8.941485
B11: Total monthly cost incl. hosting | C11: ='Cost Savings'!E35 -> 21.617633
B14: Business case | E14: Why the cost is this low
B15: Metric | C15: Value | E15: • One structured AI call per email or note — no agent loop, no embeddings, no vector database.
B16: Manual CRM work per month (today) | C16: ='Cost Savings'!E15 -> 2720 | E16: • Matching, approvals and the Daily Brief are plain code: zero AI cost.
B17: Cost with Kaizen Copilot per month | C17: ='Cost Savings'!E26 -> 608.2843 | E17: • Results are cached per source, so nothing is processed twice; prompt caching cuts measured cost further.
B18: Savings per month | C18: ='Cost Savings'!E31 -> 2111.7157 | E18: • Measured on the prototype: 50 sources for $0.043 on gpt-6-luna.
B19: % Savings | C19: ='Cost Savings'!E32 -> 0.77636607

Sheet Inference
B2: AtliQ Sales & CRM Assistant — Inference cost
B3: One structured-output call per email thread, meeting note or Quick Capture. Blue = input/assumption, black = formula, green = link.
B4: Base Calculation
B5: Description | C5: Quantity | D5: Source / assumption | F5: Model Name | G5: Input cost($) per 1M token | H5: Output cost($) per 1M token | I5: Cost per input ($) | J5: Cost per output ($) | K5: Total cost per source ($) | L5: Total cost per month ($)
B6: System prompt + rules (tokens) | C6: 1150 | D6: Prompt is ~880 words × 1.3 tokens/word | F6: gpt-6-astra | G6: 10 | H6: 50 | I6: =G6*$C$9/1000000 -> 0.02458 | J6: =H6*$C$10/1000000 -> 0.0787 | K6: =I6+J6 -> 0.10328 | L6: =K6*$C$16 -> 72.70912
B7: Output schema sent with each call (tokens) | C7: 1100 | D7: Strict JSON schema for structured output (estimate) | F7: gpt-6.1-sol | G7: 2 | H7: 10 | I7: =G7*$C$9/1000000 -> 0.004916 | J7: =H7*$C$10/1000000 -> 0.01574 | K7: =I7+J7 -> 0.020656 | L7: =K7*$C$16 -> 14.541824
B8: Email / note text (tokens) | C8: 208 | D8: Dataset average ~110 words × 1.3, plus headers | F8: gpt-6-luna (selected) | G8: 0.1 | H8: 0.5 | I8: =G8*$C$9/1000000 -> 0.0002458 | J8: =H8*$C$10/1000000 -> 0.000787 | K8: =I8+J8 -> 0.0010328 | L8: =K8*$C$16 -> 0.7270912
B9: Total input tokens per source | C9: =SUM(C6:C8) -> 2458 | D9: Prototype measured 2,458 on average (50 sources) | F9: Prices: OpenAI API pricing page, Standard tier, Oct 2026 — verify before submitting.
B10: Total output tokens per source | C10: 1574 | D10: Prototype measured average, incl. reasoning tokens
B11: Total tokens per source | C11: =C9+C10 -> 4032 | F11: Selected model: gpt-6-luna
B12: Sellers using the tool | C12: 4 | D12: Bhavin, Dhaval, Karandeep, Jay | F12: Component | G12: Cost / Quantity
B13: Emails / notes per seller per working day | C13: 6 | D13: Assumption: client threads + meeting notes | F13: Monthly model cost (no caching) | G13: =L8 -> 0.7270912
B14: Quick Captures per seller per working day | C14: 2 | D14: Assumption: phone notes after calls | F14: Buffer for retries and prompt re-runs | G14: 0.2
B15: Working days per month | C15: 22 | F15: Monthly inference cost incl. buffer | G15: =G13*(1+G14) -> 0.87250944
B16: Total monthly volume of sources | C16: =C12*(C13+C14)*C15 -> 704 | D16: Emails + notes + captures processed per month | F16: Cost per source incl. buffer | G16: =G15/C16 -> 0.00123936
F19: Prototype check (measured)
F20: Component | G20: Value
F21: Measured cost per source, with prompt caching | G21: 0.000859
F22: Estimated cost per source, no caching | G22: =K8 -> 0.0010328
F23: Estimate vs measured | G23: =G22/G21-1 -> 0.20232829
F24: Measured: 50 dataset sources cost $0.043 in total (88% of input tokens served from cache). The estimate ignores caching, so it is conservative.

Sheet Backfill & Evals
C1: AtliQ Sales & CRM Assistant — One-time backfill and evaluation runs
C3: Token/word | D3: 1.3 | F3: No embeddings or vector database: CRM matching is deterministic code. This sheet replaces the RAG embedding sheet with the one-time history backfill and evaluation runs.
C5: Email threads (12-month history) | F5: Meeting notes (12-month history) | I5: Evaluation runs (per year)
C6: Component | D6: Quantity | F6: Component | G6: Quantity | I6: Component | J6: Quantity
C7: Number of email threads | D7: 6000 | F7: Number of meeting notes | G7: 1500 | I7: Sources in eval set | J7: 50
C8: Number of words per thread | D8: 120 | F8: Number of words per note | G8: 95 | I8: Eval runs per year | J8: 24
C9: Total number of words | D9: =D7*D8 -> 720000 | F9: Total number of words | G9: =G7*G8 -> 142500 | I9: Total source-runs | J9: =J7*J8 -> 1200
C10: Total tokens | D10: =D9*$D$3 -> 936000 | F10: Total tokens | G10: =G9*$D$3 -> 185250 | I10: Cost per source-run ($) | J10: =Inference!K8 -> 0.0010328
C11: Assumption: 4 sellers × ~6 threads/day × 250 days. Dataset average 119 words. | F11: Assumption: ~6 notes/week per seller. Dataset average 94 words. | I11: Dataset of 50 sources, re-run ~2× a month for prompt or model changes.
C13: History backfill (one-time, gpt-6-luna)
C14: Component | D14: Cost/Quantity
C15: Sources to backfill | D15: =D7+G7 -> 7500
C16: Source text tokens | D16: =D10+G10 -> 1121250
C17: Prompt + schema tokens | D17: =D15*(Inference!C6+Inference!C7) -> 16875000
C18: Total input tokens | D18: =D16+D17 -> 17996250
C19: Total output tokens | D19: =D15*Inference!C10 -> 11805000
C20: Input cost per 1M token | D20: =Inference!G8 -> 0.1
C21: Output cost per 1M token | D21: =Inference!H8 -> 0.5
C22: Total backfill cost | D22: =D18*D20/1000000+D19*D21/1000000 -> 7.702125
C25: Evaluation runs (annual)
C26: Component | D26: Cost/Quantity
C27: Source-runs per year | D27: =J9 -> 1200
C28: Cost per source-run | D28: =J10 -> 0.0010328
C29: Total eval cost per year | D29: =D27*D28 -> 1.23936
C32: Total backfill + first-year evals | D32: =D22+D29 -> 8.941485

Sheet Cost Savings
D1: AtliQ Sales & CRM Assistant — Human vs AI cost
D4: Component | E4: Quantity
D5: Sellers (founders + sales executive) | E5: 4
D6: Minutes per seller per day on CRM admin | E6: 45 | F6: Assumption: logging emails and notes, updating fields, hunting for follow-ups.
D7: Working days per month | E7: 22
D8: Pipeline reconciliation hours per month | E8: 2 | F8: Dataset: Jay spent ~2 hours reconciling the CRM before one monthly review.
D9: Human hours per month on CRM admin | E9: =E5*E6*E7/60+E8 -> 68
D12: Total monthly cost of manual CRM work
D13: Component | E13: Cost
D14: Blended cost of founder / sales time per hour | E14: 40 | F14: Assumption: replace with AtliQ's own loaded hourly cost for founders and sales.
D15: Total human cost per month | E15: =E9*E14 -> 2720
D18: Cost with Kaizen Copilot
D19: Component | E19: Cost
D20: Minutes per seller per day on Daily Brief + Review Queue | E20: 10 | F20: Assumption: approving changes and acting on the ranked brief.
D21: Residual human hours per month | E21: =E5*E20*E7/60 -> 14.666667
D22: Residual human cost | E22: =E21*E14 -> 586.66667
D23: AI inference (gpt-6-luna, incl. buffer) | E23: =Inference!G15 -> 0.87250944
D24: Backfill + evals, amortized per month | E24: ='Backfill & Evals'!D32/12 -> 0.74512375
D25: Hosting (Vercel) | E25: 20 | F25: Assumption: Vercel Pro for production (free Hobby tier for the prototype) — verify plan price. Shared database on a free tier: $0.
D26: Total cost with Kaizen Copilot | E26: =SUM(E22:E25) -> 608.2843
D29: Savings
D30: Component | E30: Value
D31: Total savings per month | E31: =E15-E26 -> 2111.7157
D32: % Savings | E32: =E31/E15 -> 0.77636607
D33: Founder / sales hours freed per month | E33: =E9-E21 -> 53.333333
D34: Annual savings | E34: =E31*12 -> 25340.588
D35: AI + hosting cost per month | E35: =SUM(E23:E25) -> 21.617633
D36: Savings per $1 of AI + hosting spend | E36: =E31/E35 -> 97.684871
D39: Business upside (not counted in savings)
D40: Component | E40: Value
D41: Pipeline value flagged at risk on 10 Jul 2026 | E41: 492000 | F41: From the prototype's Daily Brief on the AtliQ dataset: revenue tied to overdue promises, unanswered client asks and imminent deadlines.
D42: Accounts with critical items on that day | E42: 21
